{"generated":"2026-06-25T11:36:03Z","source":"USGS FDSN","hours":1,"minmag":1.0,"count":5,"events":[{"id":"nc75383921","time":"2026-06-25T11:16:52.370","lat":36.678665161133,"lon":-121.34133148193,"dep":4.8499999046326,"mag":1.23,"mtype":"md","mw":0.58,"place":"13 km S of Tres Pinos, CA"},{"id":"aka2026mmccgx","time":"2026-06-25T11:07:34.552","lat":59.789,"lon":-151.655,"dep":54.0,"mag":2.0,"mtype":"ml","mw":1.17,"place":"3 km SW of Nikolaevsk, Alaska"},{"id":"aka2026mmcbad","time":"2026-06-25T11:06:06.271","lat":59.621,"lon":-152.39,"dep":73.3,"mag":2.3,"mtype":"ml","mw":1.42,"place":"35 km WSW of Anchor Point, Alaska"},{"id":"nc75383916","time":"2026-06-25T11:01:02.250","lat":38.796333312988,"lon":-122.75333404541,"dep":1.9299999475479,"mag":1.06,"mtype":"md","mw":0.46,"place":"2 km N of The Geysers, CA"},{"id":"us6000t832","time":"2026-06-25T10:58:10.413","lat":66.64,"lon":-140.7134,"dep":11.378,"mag":4.0,"mtype":"mb","mw":4.43,"place":"133 km E of Chalkyitsik, Alaska"}]}